dars/__init__.py
dars/all.py
dars/config.py
dars/env.py
dars/js_lib.py
dars/security.py
dars/version.py
dars/backend/__init__.py
dars/backend/components.py
dars/backend/data.py
dars/backend/http.py
dars/backend/json_utils.py
dars/backend/route_loader.py
dars/backend/ssr.py
dars/cli/__init__.py
dars/cli/dpm.py
dars/cli/hot_reload.py
dars/cli/main.py
dars/cli/preview.py
dars/cli/translations.py
dars/cli/doctor/__init__.py
dars/cli/doctor/detect.py
dars/cli/doctor/doctor.py
dars/cli/doctor/installers.py
dars/cli/doctor/persist.py
dars/cli/doctor/preflight.py
dars/cli/doctor/ui.py
dars/components/__init__.py
dars/components/advanced/__init__.py
dars/components/advanced/accordion.py
dars/components/advanced/card.py
dars/components/advanced/file_upload.py
dars/components/advanced/head.py
dars/components/advanced/modal.py
dars/components/advanced/navbar.py
dars/components/advanced/outlet.py
dars/components/advanced/table.py
dars/components/advanced/tabs.py
dars/components/basic/__init__.py
dars/components/basic/audio.py
dars/components/basic/button.py
dars/components/basic/checkbox.py
dars/components/basic/container.py
dars/components/basic/datepicker.py
dars/components/basic/image.py
dars/components/basic/input.py
dars/components/basic/link.py
dars/components/basic/markdown.py
dars/components/basic/page.py
dars/components/basic/progressbar.py
dars/components/basic/radiobutton.py
dars/components/basic/section.py
dars/components/basic/select.py
dars/components/basic/slider.py
dars/components/basic/spinner.py
dars/components/basic/text.py
dars/components/basic/textarea.py
dars/components/basic/tooltip.py
dars/components/basic/video.py
dars/components/layout/__init__.py
dars/components/layout/anchor.py
dars/components/layout/flex.py
dars/components/layout/grid.py
dars/components/visualization/__init__.py
dars/components/visualization/chart.py
dars/components/visualization/table.py
dars/core/__init__.py
dars/core/app.py
dars/core/component.py
dars/core/events.py
dars_framework-1.8.8.dist-info/licenses/LICENSE
dars_framework-1.8.8.dist-info/METADATA
dars_framework-1.8.8.dist-info/WHEEL
dars_framework-1.8.8.dist-info/entry_points.txt
dars_framework-1.8.8.dist-info/top_level.txt
dars_framework-1.8.8.dist-info/RECORD
