Metadata-Version: 2.4
Name: dars_framework
Version: 1.8.8
Summary: Dars is a Full-Stack multiplatform Python UI framework for building modern, interactive web and desktop apps with Python code. Seamlessly integrated with FastAPI, it allows you to build complete applications with Server-Side Rendering (SSR) and reactive SPA capabilities also classic multipage html and desktop apps in a single codebase.
Author-email: ztamdev <ztadevs@gmail.com>
Maintainer-email: ztamdev <ztadevs@gmail.com>
License-Expression: MPL-2.0
Project-URL: Homepage, https://ztamdev.github.io/Dars-Framework/
Project-URL: Documentation, https://ztamdev.github.io/Dars-Framework/docs.html
Project-URL: Repository, https://github.com/ZtaMDev/Dars-Framework
Project-URL: Bug Tracker, https://github.com/ZtaMDev/Dars-Framework/issues
Project-URL: Changelog, https://github.com/ZtaMDev/Dars-Framework/releases
Keywords: ui-framework,web-framework,python-ui,static-site-generator,html-css-js,reactive,components,spa,web-development,desktop-apps,electron
Classifier: Intended Audience :: Developers
Classifier: Topic :: Software Development :: User Interfaces
Classifier: Topic :: Software Development :: Libraries :: Python Modules
Classifier: Topic :: Internet :: WWW/HTTP :: Dynamic Content
Classifier: Topic :: Internet :: WWW/HTTP :: Site Management
Classifier: Programming Language :: Python :: 3
Classifier: Programming Language :: Python :: 3.11
Classifier: Programming Language :: Python :: 3.12
Classifier: Programming Language :: Python :: 3.13
Classifier: Programming Language :: Python :: 3.14
Classifier: Programming Language :: Python :: 3 :: Only
Classifier: Operating System :: OS Independent
Classifier: Typing :: Typed
Classifier: Natural Language :: English
Requires-Python: >=3.11
License-File: LICENSE
Requires-Dist: rich==14.2.0
Requires-Dist: bs4==0.0.2
Requires-Dist: uvicorn==0.38.0
Requires-Dist: markdown2==2.5.4
Requires-Dist: requests==2.32.5
Requires-Dist: plotly==5.18.0
Requires-Dist: fastapi==0.121.1
Requires-Dist: rjsmin==1.2.5
Requires-Dist: rcssmin==1.2.2
Dynamic: license-file
